pelt/__init__.py
pelt/pelt_generator.py
pelt/pelt_snap.py
pelt_testing-1.0.2.dist-info/LICENSE.txt
pelt_testing-1.0.2.dist-info/METADATA
pelt_testing-1.0.2.dist-info/WHEEL
pelt_testing-1.0.2.dist-info/top_level.txt
pelt_testing-1.0.2.dist-info/RECORD
