Metadata-Version: 2.1
Name: pelt-testing
Version: 1.0.2
Summary: This package allows us to test algorithms and generate test data
Home-page: https://github.com/luisprooc/pelt-testing
Author: Luis Rosario
Author-email: luisprooc@gmail.com
License: UNKNOWN
Project-URL: Bug Tracker, https://github.com/luisprooc/pelt-testing/issues
Platform: UNKNOWN
Classifier: Programming Language :: Python :: 3
Classifier: License :: OSI Approved :: MIT License
Classifier: Operating System :: OS Independent
Classifier: Environment :: Console
Requires-Python: >=3.6
